Workbook

Sheet 00-总览
A1: 2026年10—12月客户参访与高端小局 · 执行总览（单场不超过5000元）
A2: 模块 | B2: 执行口径 | C2: 核对数字 | D2: 谁负责 | E2: 状态
A3: 费用 | B3: 每场决算 ≤5000 元，超了减项，不追加 | C3: 7 场合计硬顶 35000 元 | D3: 项目经理 | E3: 必须
A4: 场次 | B4: 10/22 起，周四下午；12 月最密 | C4: 参访 4 场 + 高端小局 3 场 | D4: 项目经理 | E4: 待确认
A5: 存量客户 | B5: 客户经理陪同，次日问感受 | C5: 累计不少于 60 人次，满意度 ≥90% | D5: 客户经理 | E5: 待启动
A6: 新客户 | B6: 提名邀请，5 个工作日内首联 | C6: 到场不少于 25 家，首联率 100% | D6: 客户经理 | E6: 待启动
A7: 场地 | B7: 银行贵宾室或企业现场，不租酒店 | C7: 场地费目标为 0 | D7: 会务 | E7: 待启动
A8: 礼品与嘉宾 | B8: 默认无伴手礼、无付费嘉宾、无摄影团队 | C8: 有例外须合规书面同意且仍 ≤5000 | D8: 银行合规 | E8: 必须
A9: 取舍 | B9: 陪同排不开时，11/26 并入 12/17 | C9: 12 月 3 场不减 | D9: 项目经理 | E9: 待确认
A10: 合规 | B10: 不承诺额度、利率、放款和领导出席 | C10: 话术按 14 表执行 | D10: 银行合规 | E10: 必须
A12: 今天为 2026-09-22。8 月、9 月上旬场次不再回补。本表不构成授信或业务承诺。

Sheet 01-七场日历
A1: 七场日历｜周四下午 13:30—16:30｜客户人数不含工作人员
A2: 序 | B2: 日期 | C2: 星期 | D2: 类型 | E2: 主题 | F2: 客户人数 | G2: 存量 | H2: 新客 | I2: 目的 | J2: 场地 | K2: 预算上限 | L2: 状态
A3: 1 | B3: 2026-10-22 | C3: 周四 | D3: 精品参访 | E3: 智能制造或具身智能企业 | F3: 16 | G3: 12 | H3: 4 | I3: 让老客户感到被重视 | J3: 企业现场 | K3: 5000 | L3: 待确认
A4: 2 | B4: 2026-11-05 | C4: 周四 | D4: 高端小局 | E4: 重点客户私享问诊 | F4: 12 | G4: 12 | H4: 0 | I4: 把经营问题听清楚 | J4: 银行贵宾室 | K4: 5000 | L4: 待确认
A5: 3 | B5: 2026-11-19 | C5: 周四 | D5: 精品参访 | E5: 链主企业或AI应用现场 | F5: 16 | G5: 10 | H5: 6 | I5: 老客户带新客户 | J5: 企业现场 | K5: 5000 | L5: 待确认
A6: 4 | B6: 2026-11-26 | C6: 周四 | D6: 高端小局 | E6: 意向新客闭门局 | F6: 12 | G6: 4 | H6: 8 | I6: 新客户建立信任 | J6: 银行贵宾室 | K6: 5000 | L6: 待确认
A7: 5 | B7: 2026-12-03 | C7: 周四 | D7: 精品参访 | E7: 跨境窗口或园区 | F7: 16 | G7: 10 | H7: 6 | I7: 把出海变成看得见 | J7: 园区或机构现场 | K7: 5000 | L7: 待确认
A8: 6 | B8: 2026-12-10 | C8: 周四 | D8: 精品参访 | E8: 客户点名的标杆企业 | F8: 18 | G8: 18 | H8: 0 | I8: 年底答谢 | J8: 企业现场 | K8: 5000 | L8: 待确认
A9: 7 | B9: 2026-12-17 | C9: 周四 | D9: 高端小局 | E9: 年度收官与次年预约 | F9: 16 | G9: 10 | H9: 6 | I9: 感谢并约下一次 | J9: 银行贵宾室 | K9: 5000 | L9: 待确认
A11: 相邻两场名单默认不重复。一位存量客户全季度被邀请不超过 3 次。11/26 若陪同排不开，并入 12/17，12 月场次不减。

Sheet 02-预算模板
A1: 三套预算模板（元）｜单项可调，合计不得超过 5000
A2: 费用项 | B2: 参访16人 | C2: 高端小局12人 | D2: 收官小局16人 | E2: 能不能动 | F2: 说明
A3: 场地 | B3: 0 | C3: 0 | D3: 0 | E3: 固定为0 | F3: 企业现场或银行贵宾室，不租酒店
A4: 交通 | B4: 1800 | C4: 0 | D4: 0 | E4: 参访可调 | F4: 商务车或公共交通，按实际票据
A5: 茶水或茶叙 | B5: 600 | C5: 1800 | D5: 2400 | E5: 可减不可加过线 | F5: 小局按约150元/人，不上宴请
A6: 物料 | B6: 400 | C6: 300 | D6: 400 | E6: 可减 | F6: 行程单、胸卡、服务卡，数字材料优先
A7: 应急 | B7: 400 | C7: 400 | D7: 400 | E7: 不用不花 | F7: 只在现场发生时动用
A8: 建议合计 | B8: 3200 | C8: 2500 | D8: 3200 | E8: 低于硬顶 | F8: 余量不主动花完
A9: 硬顶 | B9: 5000 | C9: 5000 | D9: 5000 | E9: 不可突破 | F9: 伴手礼、付费嘉宾、摄影团队默认不做
A11: 若合规书面同意采购伴手礼，从余量列支，整场仍不得超过 5000 元。

Sheet 03-决算闸门
A1: 单场决算闸门｜填写实际金额后自动判定｜任一科目或合计大于 5000 即超支
A2: 场次 | B2: 日期 | C2: 类型 | D2: 场地 | E2: 交通 | F2: 茶歇 | G2: 物料 | H2: 应急 | I2: 其他 | J2: 合计 | K2: 判定 | L2: 超支后的动作
A3: 10/22 参访 | B3: 2026-10-22 | C3: 精品参访 | J3: =SUM(D3:I3) | K3: =IF(COUNT(D3:I3)=0,"待填",IF(J3>5000,"超支","合格")) | L3: =IF(K3="超支","下一场改为零采购","")
A4: 11/5 小局 | B4: 2026-11-05 | C4: 高端小局 | J4: =SUM(D4:I4) | K4: =IF(COUNT(D4:I4)=0,"待填",IF(J4>5000,"超支","合格")) | L4: =IF(K4="超支","下一场改为零采购","")
A5: 11/19 参访 | B5: 2026-11-19 | C5: 精品参访 | J5: =SUM(D5:I5) | K5: =IF(COUNT(D5:I5)=0,"待填",IF(J5>5000,"超支","合格")) | L5: =IF(K5="超支","下一场改为零采购","")
A6: 11/26 小局 | B6: 2026-11-26 | C6: 高端小局 | J6: =SUM(D6:I6) | K6: =IF(COUNT(D6:I6)=0,"待填",IF(J6>5000,"超支","合格")) | L6: =IF(K6="超支","下一场改为零采购","")
A7: 12/3 参访 | B7: 2026-12-03 | C7: 精品参访 | J7: =SUM(D7:I7) | K7: =IF(COUNT(D7:I7)=0,"待填",IF(J7>5000,"超支","合格")) | L7: =IF(K7="超支","下一场改为零采购","")
A8: 12/10 参访 | B8: 2026-12-10 | C8: 精品参访 | J8: =SUM(D8:I8) | K8: =IF(COUNT(D8:I8)=0,"待填",IF(J8>5000,"超支","合格")) | L8: =IF(K8="超支","下一场改为零采购","")
A9: 12/17 收官 | B9: 2026-12-17 | C9: 高端小局 | J9: =SUM(D9:I9) | K9: =IF(COUNT(D9:I9)=0,"待填",IF(J9>5000,"超支","合格")) | L9: =IF(K9="超支","下一场改为零采购","")
A10: 七场合计 | J10: =SUM(J3:J9) | K10: =IF(J10>35000,"超全年硬顶","全年硬顶内")
A12: 填写 D–I 列实际支出。合计大于 5000 时判定为超支，下一场只保留零成本场地和自带茶水。其他列请不要写入礼品，除非合规已书面同意。

Sheet 04-首场倒排
A1: 第一场 10月22日参访倒排｜自 9月23日启动
A2: 日期 | B2: 星期 | C2: 动作 | D2: 交付物 | E2: 负责人角色 | F2: 姓名 | G2: 状态
A3: 2026-09-23 | B3: 周三 | C3: 确认 7 场框架和单场 5000 元硬顶 | D3: 会议纪要 | E3: 四方联系人 | G3: 待启动
A4: 2026-09-24 | B4: 周四 | C4: 每位客户经理提交重点客户 8 家、意向新客 5 家 | D4: 客户名单 | E4: 客户经理 | G4: 待启动
A5: 2026-09-28 | B5: 周一 | C5: 储备至少 3 家零场地费、愿意接待的企业 | D5: 候选企业名单 | E5: 项目办/科企联 | G5: 待启动
A6: 2026-09-30 | B6: 周三 | C6: 合规确认邀约话术；默认不采购伴手礼 | D6: 口径确认 | E6: 银行合规 | G6: 待启动
A7: 2026-10-08 | B7: 周四 | C7: 国庆后敲定 10/22 被访企业、线路和客户名单 | D7: 任务书一页 | E7: 项目经理 | G7: 待启动
A8: 2026-10-09 | B8: 周五 | C8: 客户经理一对一发出邀请，不在公开群海投 | D8: 邀约记录 | E8: 客户经理 | G8: 待启动
A9: 2026-10-14 | B9: 周三 | C9: 确认名单：存量约 12 人、新客约 4 人 | D9: 出席名单 | E9: 项目经理 | G9: 待启动
A10: 2026-10-16 | B10: 周五 | C10: 客户经理陪同表；服务卡印制不超过物料预算 | D10: 陪同表 | E10: 项目办 | G10: 待启动
A11: 2026-10-19 | B11: 周一 | C11: 预走访：动线 90 分钟、无拍摄区、安全口 | D11: 预走访记录 | E11: 会务 | G11: 待启动
A12: 2026-10-21 | B12: 周三 | C12: 电话确认到场；核对交通安排仍在预算内 | D12: 到场确认 | E12: 客户经理 | G12: 待启动
A13: 2026-10-22 | B13: 周四 | C13: 13:30—16:30 参访；离场前完成服务卡 | D13: 服务卡 | E13: 全体陪同 | G13: 待启动
A14: 2026-10-23 | B14: 周五 | C14: 次日单独问感受，记录满意/一般/不满意 | D14: 回访记录 | E14: 客户经理 | G14: 待启动
... A16: 2026-10-29 | B16: 周四 | C16: 新客户完成第一次联系 | D16: 联系记录 | E16: 客户经理 | G16: 待启动
A18: 10 月 1 日至 7 日为国庆假期，不安排客户活动。

Sheet 05-后续节点
A1: 第2至第7场关键节点｜邀请一律一对一，不公开海投
A2: 节点 | B2: 11/5 小局 | C2: 11/19 参访 | D2: 11/26 新客局 | E2: 12/3 参访 | F2: 12/10 答谢参访 | G2: 12/17 收官 | H2: 负责人
A3: 锁定场地/企业 | B3: 2026-10-15 | C3: 2026-10-30 | D3: 2026-11-05 | E3: 2026-11-12 | F3: 2026-11-20 | G3: 2026-11-26 | H3: 项目经理
A4: 名单确认 | B4: 2026-10-22 | C4: 2026-11-05 | D4: 2026-11-12 | E4: 2026-11-19 | F4: 2026-11-26 | G4: 2026-12-03 | H4: 客户经理
A5: 发出邀请 | B5: 2026-10-23 | C5: 2026-11-06 | D5: 2026-11-13 | E5: 2026-11-20 | F5: 2026-11-27 | G5: 2026-12-04 | H5: 客户经理
A6: 到场确认 | B6: 2026-11-04 | C6: 2026-11-18 | D6: 2026-11-25 | E6: 2026-12-02 | F6: 2026-12-09 | G6: 2026-12-16 | H6: 客户经理
A7: 活动日 | B7: 2026-11-05 | C7: 2026-11-19 | D7: 2026-11-26 | E7: 2026-12-03 | F7: 2026-12-10 | G7: 2026-12-17 | H7: 全体
A8: 次日满意度 | B8: 2026-11-06 | C8: 2026-11-20 | D8: 2026-11-27 | E8: 2026-12-04 | F8: 2026-12-11 | G8: 2026-12-18 | H8: 客户经理
A9: 新客第5个工作日 | B9: 2026-11-12 | C9: 2026-11-26 | D9: 2026-12-03 | E9: 2026-12-10 | F9: 2026-12-17 | G9: 2026-12-24 | H9: 客户经理
A11: 11/19 与 11/26 间隔一周，两场名单不要重复。新客局若取消，把已邀请的新客户改约到 12/17，并在当天说明改期原因。

Sheet 06-即日行动
A1: 即日行动清单｜9月23日至10月22日
A2: 日期 | B2: 动作 | C2: 完成标准 | D2: 负责人 | E2: 完成
A3: 2026-09-23 | B3: 四方确认费用硬顶和 7 场安排 | C3: 纪要写明单场 ≤5000、12 月不减场 | E3: 待启动
A4: 2026-09-24 | B4: 客户经理提交名单 | C4: 每人：存量重点 8 家、意向新客 5 家 | E4: 待启动
A5: 2026-09-28 | B5: 参访企业储备 | C5: 3 家企业同意免费接待并接受拍摄限制 | E5: 待启动
A6: 2026-09-30 | B6: 话术与礼品口径 | C6: 合规书面确认：默认无伴手礼、不承诺授信 | E6: 待启动
A7: 2026-10-08 | B7: 第一场立项 | C7: 企业、线路、16 位客户、预算表同时定稿 | E7: 待启动
A8: 2026-10-09 | B8: 发出邀请 | C8: 每一家都有客户经理邀约记录 | E8: 待启动
A9: 2026-10-19 | B9: 预走访 | C9: 动线、茶水、交通报价都落在 5000 元内 | E9: 待启动
A10: 2026-10-22 | B10: 举办第一场 | C10: 服务卡与当天决算草稿同时收回 | E10: 待启动
A11: 2026-10-23 | B11: 满意度回访 | C11: 出席客户均有满意/一般/不满意记录 | E11: 待启动
A13: 负责人一栏在 9 月 23 日会上填姓名。没有姓名的事项不开始。

Sheet 07-客户出席回访
A1: 客户出席与回访｜一场一行一位客户｜用来统计满意度和人次
A2: 场次 | B2: 日期 | C2: 客户经理 | D2: 企业名称 | E2: 联系人 | F2: 手机 | G2: 客户类型 | H2: 邀约状态 | I2: 是否出席 | J2: 满意度 | K2: 一句原因 | L2: 不满意回访 | M2: 备注
A3: 10/22 参访 | B3: 2026-10-22 | C3: （示例，请覆盖） | D3: 某某科技 | G3: 存量 | H3: 待邀 | M3: 示例行
A85: 客户类型：存量 / 新客 / 转介。转介指老客户带来的新企业，计入新客成果。不满意的，2 日内必须电话回访并让项目经理知情。

Sheet 08-新客跟进
A1: 新客户跟进｜只记录新客和转介｜5 个工作日内必须有联系记录
A2: 场次 | B2: 企业名称 | C2: 来源 | D2: 陪同老客户 | E2: 客户经理 | F2: 出席 | G2: 离场对接人 | H2: 第5个工作日 | I2: 是否已联系 | J2: 联系日期 | K2: 客户原话要点 | L2: 下一步 | M2: 状态
A3: 11/26 新客局 | B3: （示例，请覆盖） | C3: 转介 | L3: 5个工作日内拜访或电话 | M3: 待联系
A45: 不在本表记录授信结论。联系结果只写：已联系、约到下次、暂无需求、联系不上。

Sheet 09-服务事项
A1: 服务事项｜每家客户最多先记一件事｜10 个工作日内给第一次反馈
A2: 事项编号 | B2: 场次 | C2: 企业名称 | D2: 客户类型 | E2: 客户要办的一件事 | F2: 客户经理 | G2: 承诺反馈日 | H2: 状态 | I2: 反馈内容 | J2: 是否涉及融资
A3: 1022-001 | B3: 10/22 参访 | C3: （示例） | D3: 存量 | E3: 想了解订单周转可以准备哪些材料 | G3: 2026-11-05 | H3: 待反馈 | J3: 是
A45: 涉及融资的，只反馈材料准备或是否进入银行正常流程，不写额度、利率和放款时间。

Sheet 10-指标
A1: 指标自动汇总｜出席与满意度来自「07-客户出席回访」，新客联系来自「08-新客跟进」
A2: 指标 | B2: 目标 | C2: 当前数字 | D2: 怎么数 | E2: 是否达到 | F2: 说明
A3: 存量客户出席人次 | B3: 60 | C3: =COUNTIFS('07-客户出席回访'!G:G,"存量",'07-客户出席回访'!I:I,"是") | D3: 类型=存量 且 出席=是 | E3: =IF(C3="","待填",IF(C3>=B3,"达到","未达到"))
A4: 新客户出席 | B4: 25 | C4: =COUNTIFS('07-客户出席回访'!G:G,"新客",'07-客户出席回访'!I:I,"是")+COUNTIFS('07-客户出席回访'!G:G,"转介",'07-客户出席回访'!I:I,"是") | D4: 新客+转介，且出席=是 | E4: =IF(C4="","待填",IF(C4>=B4,"达到","未达到"))
A5: 转介到场 | B5: 8 | C5: =COUNTIFS('07-客户出席回访'!G:G,"转介",'07-客户出席回访'!I:I,"是") | D5: 类型=转介 且 出席=是 | E5: =IF(C5="","待填",IF(C5>=B5,"达到","未达到"))
A6: 已填满意度份数 | B6: — | C6: =COUNTIF('07-客户出席回访'!J:J,"满意")+COUNTIF('07-客户出席回访'!J:J,"一般")+COUNTIF('07-客户出席回访'!J:J,"不满意") | D6: 有满意度记录的人数 | E6: —
A7: 满意份数 | B7: — | C7: =COUNTIF('07-客户出席回访'!J:J,"满意") | D7: 满意度=满意 | E7: —
A8: 满意度 | B8: ≥90% | C8: =IF(C6=0,"",C7/C6) | D8: 满意份数 / 已填份数 | E8: =IF(C8="","待填",IF(C8>=0.9,"达到","未达到"))
A9: 新客已联系 | B9: — | C9: =COUNTIF('08-新客跟进'!I:I,"是") | D9: 新客表中已联系=是 | E9: —
A10: 新客应联系 | B10: — | C10: =COUNTIF('08-新客跟进'!F:F,"是") | D10: 新客表中出席=是 | E10: —
A11: 新客联系率 | B11: 100% | C11: =IF(C10=0,"",C9/C10) | D11: 已联系 / 应联系 | E11: =IF(C11="","待填",IF(C11>=1,"达到","未达到"))
A12: 满意度目标看比例，不看绝对份数。新客 5 日内联系率 = 已联系 / 应联系，目标 100%。示例行请覆盖，否则会被算进数字。

Sheet 11-责任与人力
A1: 责任与小场人力｜先填姓名，没有姓名的岗位视为未到位
A2: 事项或岗位 | B2: 人数 | C2: 拍板人 | D2: 办理人 | E2: 姓名 | F2: 备份 | G2: 一场要做完的事
A3: 项目经理 | B3: 1 | C3: 项目经理 | D3: 项目经理 | G3: 控预算、控时间、处理不满意升级
A4: 客户经理陪同 | B4: 4—8 | C4: 客户经理 | D4: 客户经理 | G4: 邀请、陪同、次日回访、新客首联
A5: 会务 | B5: 1 | C5: 项目经理 | D5: 会务 | G5: 场地、交通、茶水、物料，报价不超 5000
A6: 记录 | B6: 1 | C6: 项目经理 | D6: 记录 | G6: 服务卡收回，当天录入台账
A7: 合规窗口 | B7: 1 | C7: 银行合规 | D7: 银行合规 | G7: 审邀请话术；不必全程在场
A8: 被访企业引导 | B8: 1 | C8: 被访企业 | D8: 被访企业 | G8: 路线、安全、无拍摄区
A9: 参访企业落实 | B9: — | C9: 项目经理 | D9: 科企联/项目办 | G9: 书面确认免费接待和拍摄边界
A10: 预算不超 5000 | B10: — | C10: 项目经理 | D10: 会务 | G10: 决算录入闸门表
A12: 小局可以不设被访企业引导。客户经理人数按自己客户的数量增减，但不把客户交给不认识的人陪同。

Sheet 12-现场检查
A1: 现场检查｜每场复制使用｜场次： 日期： 项目经理：
A2: 时点 | B2: 检查项 | C2: 适用 | D2: 完成 | E2: 姓名
A3: 立项 | B3: 预算表合计 ≤5000，且无付费嘉宾、无摄影团队 | C3: 全部 | D3: 否
A4: 立项 | B4: 被访企业书面同意免费接待，写明无拍摄区 | C4: 参访 | D4: 否
A5: 邀请前 | B5: 话术不含额度、利率、放款、领导保证出席 | C5: 全部 | D5: 否
A6: T-5 | B6: 交通和茶歇报价复核，超了已减项 | C6: 全部 | D6: 否
A7: T-1 | B7: 每位客户都有陪同的客户经理 | C7: 全部 | D7: 否
A8: 当天开始 | B8: 13:30 开始；告知不收费、不承诺贷款 | C8: 全部 | D8: 否
A9: 参访中 | B9: 动线 90 分钟内，引导在场 | C9: 参访 | D9: 否
A10: 离场前 | B10: 每家客户有一张服务卡，客户点头 | C10: 全部 | D10: 否
A11: 离场前 | B11: 新客户知道对接人姓名 | C11: 有新客时 | D11: 否
A12: 当天 | B12: 票据装袋，准备录入决算闸门 | C12: 全部 | D12: 否
A13: 次日 | B13: 出席客户都有满意度 | C13: 全部 | D13: 否
A14: 2日内 | B14: 不满意客户已电话，项目经理已知情 | C14: 如有 | D14: 否
A16: 完成栏改为“是”才算过。参访场次中标成“参访”的项目不能空。

Sheet 13-风险与边界
A1: 风险与边界｜开场先说不收费、不承诺贷款
A2: 风险 | B2: 出现时怎么处理 | C2: 谁处理 | D2: 程度
A3: 报价超过 5000 元 | B3: 减交通、茶歇或物料；减完仍超过就换零成本场地 | C3: 项目经理 | D3: 高
A4: 被访企业临时取消 | B4: 改到银行贵宾室，同主题小局，已确认客户照常接待 | C4: 项目经理 | D4: 高
A5: 客户问能批多少 | B5: 回答由银行独立审批；不给区间、不给时间 | C5: 客户经理 | D5: 高
A6: 有人现场拉业务或收费 | B6: 当场制止并请离，取消后续资格 | C6: 项目经理 | D6: 高
A7: 客户不满意 | B7: 2 日内客户经理电话；项目经理记录原因 | C7: 客户经理 | D7: 中
A8: 新客 5 日内没人联系 | B8: 项目经理当天改派另一位客户经理 | C8: 项目经理 | D8: 高
A9: 同一客户被连续邀请 | B9: 相邻场次默认不重复，季度不超过 3 次 | C9: 项目经理 | D9: 中
A10: 想加伴手礼 | B10: 先过合规；总额仍须 ≤5000，否则不做 | C10: 银行合规 | D10: 中
A11: 拍摄到不该拍的区域 | B11: 当场删除，书面说明 | C11: 会务 | D11: 高
A13: 金融业务由泰隆银行独立尽调、审批。活动方不代替银行作授信判断。

Sheet 14-话术
A1: 可直接使用的话术｜方括号处替换成当天信息
A2: 场景 | B2: 怎么说 | C2: 不要补上的话
A3: 邀请老客户 | B3: 【姓名】总，10月22日下午我们安排了一场小范围企业参访，半天，我陪您一起去。人不超二十位，不收费。您看这天是否方便？ | C3: 不要说保证见到某位领导，不要说去了有额度。
A4: 邀请新客户 | B4: 我们和复旦、科企联一起，请少数企业去现场看一家公司，银行客户经理会陪同。不收费，也不在现场谈贷款结果。如果您愿意来，我负责接您，活动后 5 个工作日内再跟您联系一次。 | C4: 不要说内部指标、隐形名额、送礼开户。
A5: 老客户带新 | B5: 如果您有一位合适的同行或合作伙伴，可以一起来。名额有限，我先替您留一个位子。 | C5: 不要承诺对方一定能成为我行客户。
A6: 开场 | B6: 今天下午只做一件事：把大家带来的问题记清楚。活动不收费。贷款能否办理，由泰隆银行按自己的流程审批，现场不作承诺。 | C6: 不要介绍具体产品价格和通过率。
A7: 离场 | B7: 今天我为您记下的是【一件事】。下一步由我来办，最晚【日期】前给您回复。您看是不是这一件？ | C7: 不要当场加第二件、第三件把客户留住。
A8: 次日回访 | B8: 昨天的参访，哪一点对您有用，哪一点浪费了您的时间？我想听一句实在的。 | C8: 不要群发同一段话。
A9: 不满意 | B9: 昨天那件事没安排好，是我们的问题。我今天先处理【具体动作】，处理完再告诉您。 | C9: 不要解释成客户误会了。
A10: 新客首次联系 | B10: 谢谢您昨天来。我是您的对接人【姓名】。您当时提到【一件事】，我这周把可以准备的资料或可介绍的同事跟您说清楚。是否办理业务，还是要走银行正常流程。 | C10: 不要在电话里做审批判断。
A11: 暂不适合 | B11: 以目前这件需求，银行这条线暂时对不上，原因是【客观原因】。我可以介绍【另一条合规渠道】，是否使用由您决定。您仍在我们的客户名单里，下一场合适的活动我再单独邀您。 | C11: 不要说再等等来拖延，不要留下负面评价。
A13: 对外提到泰隆银行名称、标识和案例前，先经银行指定窗口看过。
